muranorepository
