Metadata-Version: 1.0
Name: murano-repository
Version: 0.4.a28.g0c584bc
Summary: Murano Metadata Repository
Home-page: https://launchpad.net/murano
Author: Mirantis, Inc.
Author-email: openstack-dev@lists.openstack.org
License: Apache Software License
Platform: UNKNOWN
